yocto/__init__.py
yocto/myClass.py
yocto-0.1.2.dist-info/LICENCE.txt
yocto-0.1.2.dist-info/METADATA
yocto-0.1.2.dist-info/WHEEL
yocto-0.1.2.dist-info/top_level.txt
yocto-0.1.2.dist-info/RECORD
