Metadata-Version: 2.1
Name: yocto
Version: 0.1.2
Summary: yocto library, need to include MIA attack
Home-page: https://yocto.readthedocs.io/
Author: Nathan Brunet
Author-email: nathan.brunet@inria.fr
License: MIT
Classifier: Intended Audience :: Developers
Classifier: License :: OSI Approved :: MIT License
Classifier: Programming Language :: Python
Classifier: Programming Language :: Python :: 3.8
Classifier: Programming Language :: Python :: 3.9
Classifier: Operating System :: OS Independent
License-File: LICENCE.txt
Requires-Dist: numpy
Requires-Dist: pandas
